krlio/__init__.py
krlio-0.0.3.dist-info/DESCRIPTION.rst
krlio-0.0.3.dist-info/METADATA
krlio-0.0.3.dist-info/RECORD
krlio-0.0.3.dist-info/WHEEL
krlio-0.0.3.dist-info/metadata.json
krlio-0.0.3.dist-info/top_level.txt
